rest_framework_material/__init__.py
rest_framework_material/admin.py
rest_framework_material/apps.py
rest_framework_material/migrations/__init__.py
rest_framework_material/models.py
rest_framework_material/templates/rest_framework/api.html
rest_framework_material/templates/rest_framework/filters/base.html
rest_framework_material/templates/rest_framework/filters/ordering.html
rest_framework_material/templates/rest_framework/filters/search.html
rest_framework_material/templates/rest_framework/horizontal/checkbox.html
rest_framework_material/templates/rest_framework/horizontal/checkbox_multiple.html
rest_framework_material/templates/rest_framework/horizontal/dict_field.html
rest_framework_material/templates/rest_framework/horizontal/fieldset.html
rest_framework_material/templates/rest_framework/horizontal/form.html
rest_framework_material/templates/rest_framework/horizontal/input.html
rest_framework_material/templates/rest_framework/horizontal/list_field.html
rest_framework_material/templates/rest_framework/horizontal/list_fieldset.html
rest_framework_material/templates/rest_framework/horizontal/radio.html
rest_framework_material/templates/rest_framework/horizontal/select.html
rest_framework_material/templates/rest_framework/horizontal/select_multiple.html
rest_framework_material/templates/rest_framework/horizontal/textarea.html
rest_framework_material/templates/rest_framework/inline/checkbox.html
rest_framework_material/templates/rest_framework/inline/checkbox_multiple.html
rest_framework_material/templates/rest_framework/inline/dict_field.html
rest_framework_material/templates/rest_framework/inline/fieldset.html
rest_framework_material/templates/rest_framework/inline/form.html
rest_framework_material/templates/rest_framework/inline/input.html
rest_framework_material/templates/rest_framework/inline/list_field.html
rest_framework_material/templates/rest_framework/inline/list_fieldset.html
rest_framework_material/templates/rest_framework/inline/radio.html
rest_framework_material-0.2.3.dist-info/LICENSE
rest_framework_material-0.2.3.dist-info/METADATA
rest_framework_material-0.2.3.dist-info/WHEEL
rest_framework_material-0.2.3.dist-info/RECORD
