Metadata-Version: 2.1
Name: rest-framework-material
Version: 0.2.3
Summary: Material design for Django REST Framework API
Home-page: https://github.com/youzarsiph/rest-framework-material/
License: MIT
Author: Yousef Abu Shanab
Author-email: josephyousef249@gmail.com
Requires-Python: >=3.7
Classifier: License :: OSI Approved :: MIT License
Classifier: Programming Language :: Python :: 3
Classifier: Programming Language :: Python :: 3.7
Classifier: Programming Language :: Python :: 3.8
Classifier: Programming Language :: Python :: 3.9
Classifier: Programming Language :: Python :: 3.10
Classifier: Programming Language :: Python :: 3.11
Requires-Dist: django (>=3.0)
Requires-Dist: djangorestframework (>=3.14)
Project-URL: Repository, https://github.com/youzarsiph/rest-framework-material/
